<?xml version="1.0" encoding="UTF-8"?>
<objects serializationModel="Studio.02.02.00">
	<object class="AudioFile" id="{11e7123a-cb37-4b7e-8c57-1f91ca5332b6}">
		<property name="assetPath">
			<value>guts009.wav</value>
		</property>
		<property name="frequencyInKHz">
			<value>44.0999985</value>
		</property>
		<property name="channelCount">
			<value>2</value>
		</property>
		<property name="length">
			<value>0.62498866213151927</value>
		</property>
		<relationship name="masterAssetFolder">
			<destination>{b40148d5-2270-41a7-93a1-0358a5d54c0e}</destination>
		</relationship>
	</object>
</objects>
